{"1": "giảm", "2": "Mùa thu", "3": "Hậu Lê", "4": "Bóng chuyền", "5": "khoảng cách", "6": "thuận", "7": "Tất cả", "8": "Đúng", "9": "Hidro", "10": "vua", "11": "Hàn Quốc", "12": "Twenty", "13": "Lão Hạc", "14": "0", "15": "Thể rắn", "16": "2", "17": "Bà Triệu", "18": "Câu lạc bộ Hải Phòng", "19": "Hội họa", "20": "One (1)", "21": "Đông y", "22": "Sai", "23": "đồng biến", "24": "elip", "25": "vận động", "26": "Chữ người tử tù", "27": "Nguyễn Trung Trực", "28": "lớn", "29": "Điệp viên 007", "30": "Hòa Bình", "31": "Ruột non", "32": "Đông Nam Bộ"}